feldera/__init__.py
feldera/_callback_runner.py
feldera/_helpers.py
feldera/enums.py
feldera/output_handler.py
feldera/pipeline.py
feldera/pipeline_builder.py
feldera/runtime_config.py
feldera/stats.py
feldera/testutils.py
feldera/testutils_oidc.py
feldera/types.py
feldera/rest/__init__.py
feldera/rest/_helpers.py
feldera/rest/_httprequests.py
feldera/rest/config.py
feldera/rest/errors.py
feldera/rest/feldera_client.py
feldera/rest/feldera_config.py
feldera/rest/pipeline.py
feldera/rest/sql_table.py
feldera/rest/sql_view.py
feldera-0.235.0.dist-info/METADATA
feldera-0.235.0.dist-info/WHEEL
feldera-0.235.0.dist-info/top_level.txt
feldera-0.235.0.dist-info/RECORD
