Metadata-Version: 2.4
Name: feldera
Version: 0.235.0
Summary: The feldera python client
Author-email: Feldera Team <dev@feldera.com>
License-Expression: MIT
Project-URL: Homepage, https://www.feldera.com
Project-URL: Documentation, https://docs.feldera.com/python
Project-URL: Repository, https://github.com/feldera/feldera
Project-URL: Issues, https://github.com/feldera/feldera/issues
Keywords: feldera,python
Classifier: Programming Language :: Python :: 3.10
Classifier: Operating System :: OS Independent
Requires-Python: >=3.10
Requires-Dist: requests
Requires-Dist: pandas>=2.1.2
Requires-Dist: typing-extensions
Requires-Dist: numpy>=2.2.4
Requires-Dist: pretty-errors
Requires-Dist: ruff>=0.6.9
Requires-Dist: PyJWT>=2.8.0
